pypref/Preferences.py
pypref/__init__.py
pypref/__pkginfo__.py
pypref-3.1.0.dist-info/LICENSE.txt
pypref-3.1.0.dist-info/METADATA
pypref-3.1.0.dist-info/WHEEL
pypref-3.1.0.dist-info/top_level.txt
pypref-3.1.0.dist-info/RECORD
