Metadata-Version: 2.1
Name: pypref
Version: 3.1.0
Summary: PYthon PREFrences or pypref is a python implementation to creating application's configuration, preferences or settings file and dynamically interacting, updating and pulling them. Most applications have default preferences and in general those are created and stored in a text file (.ini, xml, json, etc). 
Home-page: http://bachiraoun.github.io/pypref/
Author: Bachir AOUN
Author-email: bachir.aoun@e-aoun.com
License: GNU
Download-URL: https://github.com/bachiraoun/pypref
Platform: Windows
Platform: Linux
Platform: Mac OS-X
Platform: Unix
Classifier: Development Status :: 4 - Beta
Classifier: Intended Audience :: Science/Research
Classifier: Intended Audience :: Developers
Classifier: License :: OSI Approved :: GNU Affero General Public License v3
Classifier: Programming Language :: Python
Classifier: Programming Language :: Python :: 2
Classifier: Programming Language :: Python :: 2.6
Classifier: Programming Language :: Python :: 2.7
Classifier: Topic :: Software Development
Classifier: Topic :: Software Development :: Build Tools
Classifier: Topic :: Scientific/Engineering
Classifier: Operating System :: Microsoft :: Windows
Classifier: Operating System :: POSIX
Classifier: Operating System :: Unix
Classifier: Operating System :: MacOS
